Pimydoc-0.2.9.dist-info/DESCRIPTION.rst
Pimydoc-0.2.9.dist-info/METADATA
Pimydoc-0.2.9.dist-info/RECORD
Pimydoc-0.2.9.dist-info/WHEEL
Pimydoc-0.2.9.dist-info/entry_points.txt
Pimydoc-0.2.9.dist-info/metadata.json
Pimydoc-0.2.9.dist-info/top_level.txt
pimydoc/__init__.py
pimydoc/pimydoc.py
