Metadata-Version: 2.0
Name: Pimydoc
Version: 0.2.9
Summary: Insert and update blocks of text into text files
Home-page: https://github.com/suizokukan/pimydoc
Author: Xavier Faure (suizokukan)
Author-email: suizokukan@orange.fr
License: GPL-3.0
Keywords: file manager tags
Platform: UNKNOWN
Classifier: Development Status :: 4 - Beta
Classifier: Intended Audience :: End Users/Desktop
Classifier: Topic :: Utilities
Classifier: License :: OSI Approved :: GNU General Public License v3 (GPLv3)
Classifier: Programming Language :: Python :: 3
